cgservo/__init__.py
cgservo/pca9685.py
cgservo/servo.py
cgservo-1.2.dist-info/LICENSE
cgservo-1.2.dist-info/METADATA
cgservo-1.2.dist-info/WHEEL
cgservo-1.2.dist-info/top_level.txt
cgservo-1.2.dist-info/RECORD
